<recipeItem>
   <name>Hummus</name>
   <type>starter</type>
   <picture>cukio_2015.04.05_19.09.03.jpg</picture>
   <ingredients class="java.util.ArrayList">
      <string>250 g garbanzos cocidos</string>
      <string>25 ml zumo de limón</string>
      <string>1 pizca comino</string>
      <string>1 pizca pimentón</string>
      <string>1 pizca aceite</string>
      <string>1 pizca sal</string>
   </ingredients>
   <steps class="java.util.ArrayList">
      <string>Añadir todos los ingredientes dentro del bol y cocinar. A continuación, triturar. Tipo de cocción: rápida: 4 minutos.</string>
   </steps>
   <author>Programada en el robot</author>
   <vegetarian>true</vegetarian>
   <portions>2</portions>
   <minutes>6</minutes>
   <language>Spanish</language>
   <tip></tip>
</recipeItem>